tvb_ext_bucket/__init__.py
tvb_ext_bucket/_version.py
tvb_ext_bucket/ebrains_drive_wrapper.py
tvb_ext_bucket/exceptions.py
tvb_ext_bucket/handlers.py
tvb_ext_bucket/bucket_api/__init__.py
tvb_ext_bucket/bucket_api/bucket_api.py
tvb_ext_bucket/bucket_api/buckets.py
tvb_ext_bucket/bucket_api/dataproxy_file.py
tvb_ext_bucket/logger/__init__.py
tvb_ext_bucket/logger/builder.py
tvb_ext_bucket/logger/logging.conf
tvb_ext_bucket/tests/__init__.py
tvb_ext_bucket/tests/test_bucket.py
tvb_ext_bucket/tests/test_buckets.py
tvb_ext_bucket/tests/test_dataproxy_file.py
tvb_ext_bucket/tests/test_drive_wrapper.py
tvb_ext_bucket/tests/test_handlers.py
tvb_ext_bucket-2.0.0.data/data/etc/jupyter/jupyter_server_config.d/tvb_ext_bucket.json
tvb_ext_bucket-2.0.0.data/data/share/jupyter/labextensions/tvb-ext-bucket/package.json
tvb_ext_bucket-2.0.0.data/data/share/jupyter/labextensions/tvb-ext-bucket/static/728.6abe3f469f1ce32580ec.js
tvb_ext_bucket-2.0.0.data/data/share/jupyter/labextensions/tvb-ext-bucket/static/85.3108c9886a1f8298ee2f.js
tvb_ext_bucket-2.0.0.data/data/share/jupyter/labextensions/tvb-ext-bucket/static/acb28ef48e64b689e3e4.png
tvb_ext_bucket-2.0.0.data/data/share/jupyter/labextensions/tvb-ext-bucket/static/remoteEntry.b249e2c093409a283a29.js
tvb_ext_bucket-2.0.0.data/data/share/jupyter/labextensions/tvb-ext-bucket/static/style.js
tvb_ext_bucket-2.0.0.data/data/share/jupyter/labextensions/tvb-ext-bucket/static/third-party-licenses.json
tvb_ext_bucket-2.0.0.data/data/share/jupyter/labextensions/tvb-ext-bucket/install.json
tvb_ext_bucket-2.0.0.dist-info/METADATA
tvb_ext_bucket-2.0.0.dist-info/WHEEL
tvb_ext_bucket-2.0.0.dist-info/licenses/LICENSE
tvb_ext_bucket-2.0.0.dist-info/RECORD
