Metadata-Version: 2.3
Name: tvb-ext-bucket
Version: 2.0.0
Summary: Extension for collabs bucket interaction
Project-URL: Homepage, https://github.com/the-virtual-brain/tvb-ext-bucket
Project-URL: Bug Tracker, https://github.com/the-virtual-brain/tvb-ext-bucket/issues
Project-URL: Repository, https://github.com/the-virtual-brain/tvb-ext-bucket.git
Author-email: TVB Widgets Team <tvb.admin@thevirtualbrain.org>
License:                     GNU GENERAL PUBLIC LICENSE
License-File: LICENSE
Keywords: jupyter,jupyterlab,jupyterlab-extension
Classifier: Framework :: Jupyter
Classifier: Framework :: Jupyter :: JupyterLab
Classifier: Framework :: Jupyter :: JupyterLab :: 4
Classifier: Framework :: Jupyter :: JupyterLab :: Extensions
Classifier: Framework :: Jupyter :: JupyterLab :: Extensions :: Prebuilt
Classifier: License :: OSI Approved :: GNU General Public License (GPL)
Classifier: Programming Language :: Python
Classifier: Programming Language :: Python :: 3
Classifier: Programming Language :: Python :: 3.8
Classifier: Programming Language :: Python :: 3.9
Classifier: Programming Language :: Python :: 3.10
Classifier: Programming Language :: Python :: 3.11
Classifier: Programming Language :: Python :: 3.12
Requires-Python: >=3.8
Requires-Dist: ebrains-drive>=0.5.0
Requires-Dist: jupyter-server<3,>=2.0.1
Provides-Extra: test
Requires-Dist: coverage; extra == 'test'
Requires-Dist: pytest; extra == 'test'
Requires-Dist: pytest-asyncio; extra == 'test'
Requires-Dist: pytest-cov; extra == 'test'
Requires-Dist: pytest-jupyter[server]>=0.6.0; extra == 'test'
